src/single_cycle/Data_Memory.v
module Data_Memory(input clk, MemRead, MemWrite, input [31:0] addr, wdata, output reg [31:0] rdata);
 reg [31:0] mem[0:255];
 integer i; initial for(i=0;i<256;i=i+1) mem[i]=0;
 always @(posedge clk) if(MemWrite) mem[addr[9:2]] <= wdata;
 always @(*) if(MemRead) rdata = mem[addr[9:2]]; else rdata=0;
endmodule

ALU.v
module ALU(input [31:0] A, B, input [3:0] ctrl, output reg [31:0] result, output zero);
 always @(*) begin
  case(ctrl)
   4'b0010: result = A + B;
   4'b0110: result = A - B;
   4'b0000: result = A & B;
   4'b0001: result = A | B;
   default: result = A + B;
  endcase
 end
 assign zero = (result==0);
endmodule

RegisterFile.v
module RegisterFile(input clk, reset, input [4:0] rs1, rs2, rd, input [31:0] WriteData, input RegWrite, output [31:0] ReadData1, ReadData2);
    reg [31:0] regs[0:31];
    integer i;
    initial for(i=0;i<32;i=i+1) regs[i]=0;
    assign ReadData1 = (rs1==0)? 0 : regs[rs1];
    assign ReadData2 = (rs2==0)? 0 : regs[rs2];
    always @(posedge clk) if(RegWrite && rd!=0) regs[rd] <= WriteData;
endmodule

Immediate_Generator.v
module Immediate_Generator(
    input [31:0] instr,
    output reg [31:0] imm
);
    always @(*) begin
        case(instr[6:0])
            7'b0010011: imm = {{20{instr[31]}}, instr[31:20]};
            7'b0000011: imm = {{20{instr[31]}}, instr[31:20]};
            7'b0100011: imm = {{20{instr[31]}}, instr[31:25], instr[11:7]};
            7'b1100011: imm = {{20{instr[31]}}, instr[7], instr[30:25], instr[11:8], 1'b0};
            default: imm = 32'd0;
        endcase
    end
endmodule

ALU_Control.v
module ALU_Control(
    input [1:0] ALUOp,
    input [2:0] funct3,
    input [6:0] funct7,
    output reg [3:0] alu_ctrl
);
    always @(*) begin
        case(ALUOp)
            2'b00: alu_ctrl = 4'b0010;
            2'b01: alu_ctrl = 4'b0110;
            2'b10: begin
                case(funct3)
                    3'b000: alu_ctrl = (funct7[5]? 4'b0110 : 4'b0010);
                    3'b111: alu_ctrl = 4'b0000;
                    3'b110: alu_ctrl = 4'b0001;
                    default: alu_ctrl = 4'b0010;
                endcase
            end
            2'b11: alu_ctrl = 4'b0010;
            default: alu_ctrl = 4'b0010;
        endcase
    end
endmodule

src/single_cycle/Control_Unit.v
module Control_Unit(input [6:0] opcode, output reg Branch, MemRead, MemtoReg, MemWrite, ALUSrc, RegWrite, output reg [1:0] ALUOp);
 always @(*) begin
  Branch=0; MemRead=0; MemtoReg=0; MemWrite=0; ALUSrc=0; RegWrite=0; ALUOp=2'b00;
  case(opcode)
   7'b0110011: begin RegWrite=1; ALUOp=2'b10; end // R-type
   7'b0010011: begin RegWrite=1; ALUSrc=1; ALUOp=2'b11; end // I-type ADDI
   7'b0000011: begin RegWrite=1; ALUSrc=1; MemRead=1; MemtoReg=1; ALUOp=2'b00; end // LW
   7'b0100011: begin ALUSrc=1; MemWrite=1; ALUOp=2'b00; end // SW
   7'b1100011: begin Branch=1; ALUOp=2'b01; end // BEQ
  endcase
 end
endmodule

Instruction_Memory.v
module Instruction_Memory(input [31:0] addr, output [31:0] instr);
 reg [31:0] mem[0:255];
 integer i;
 initial begin for(i=0;i<256;i=i+1) mem[i]=32'h00000013; $readmemh("program.hex", mem); end
 assign instr = mem[addr[9:2]];
endmodule

RISCV_Top.v
module RISCV_Top(input clk, reset);
 reg [31:0] pc;
 wire [31:0] pc_plus4, instr, imm, r1, r2, alu_b, alu_res, mem_data, wb_data;
 wire Branch, MemRead, MemtoReg, MemWrite, ALUSrc, RegWrite, zero;
 wire [1:0] ALUOp; wire [3:0] alu_ctrl;
 wire [31:0] branch_target = pc + imm;
 wire take_branch = Branch & zero;
 wire [31:0] pc_next = take_branch? branch_target : pc_plus4;
 assign pc_plus4 = pc + 4;
 always @(posedge clk or posedge reset) if(reset) pc<=0; else pc<=pc_next;
 Instruction_Memory IMEM(pc, instr);
 Control_Unit CU(instr[6:0], Branch, MemRead, MemtoReg, MemWrite, ALUSrc, RegWrite, ALUOp);
 ALU_Control ALUC(ALUOp, instr[14:12], instr[31:25], alu_ctrl);
 Immediate_Generator IMM(instr, imm);
 RegisterFile RF(clk, reset, instr[19:15], instr[24:20], instr[11:7], wb_data, RegWrite, r1, r2);
 assign alu_b = ALUSrc? imm : r2;
 ALU ALUUNIT(r1, alu_b, alu_ctrl, alu_res, zero);
 Data_Memory DMEM(clk, MemRead, MemWrite, alu_res, r2, mem_data);
 assign wb_data = MemtoReg? mem_data : alu_res;
endmodule

tb/RISCV_Top_tb.v
module RISCV_Top_tb;
 reg clk, reset;
 RISCV_Top uut(clk, reset);
 initial begin clk=0; forever #5 clk=~clk; end
 initial begin $dumpfile("dump.vcd"); $dumpvars(0, RISCV_Top_tb); end
 initial begin reset=1; #15; reset=0; #300; $display("DONE regs[1]=%h regs[2]=%h regs[3]=%h", uut.RF.regs[1], uut.RF.regs[2], uut.RF.regs[3]); $finish; end
endmodule

dump.vcd
$date
	Wed Sep 23 09:45:22 2026
$end
$version
	Icarus Verilog
$end
$timescale
	1s
$end
$scope module RISCV_Top_tb $end
$var reg 1 ! clk $end
$var reg 1 " reset $end
$scope module uut $end
$var wire 1 ! clk $end
$var wire 1 " reset $end
$var wire 1 # take_branch $end
$var wire 1 $ zero $end
$var wire 32 % wb_data [31:0] $end
$var wire 32 & r2 [31:0] $end
$var wire 32 ' r1 [31:0] $end
$var wire 32 ( pc_plus4 [31:0] $end
$var wire 32 ) pc_next [31:0] $end
$var wire 32 * mem_data [31:0] $end
$var wire 32 + instr [31:0] $end
$var wire 32 , imm [31:0] $end
$var wire 32 - branch_target [31:0] $end
$var wire 32 . alu_res [31:0] $end
$var wire 4 / alu_ctrl [3:0] $end
$var wire 32 0 alu_b [31:0] $end
$var wire 1 1 RegWrite $end
$var wire 1 2 MemtoReg $end
$var wire 1 3 MemWrite $end
$var wire 1 4 MemRead $end
$var wire 1 5 Branch $end
$var wire 1 6 ALUSrc $end
$var wire 2 7 ALUOp [1:0] $end
$var reg 32 8 pc [31:0] $end
$scope module ALUC $end
$var wire 3 9 funct3 [2:0] $end
$var wire 7 : funct7 [6:0] $end
$var wire 2 ; ALUOp [1:0] $end
$var reg 4 < alu_ctrl [3:0] $end
$upscope $end
$scope module ALUUNIT $end
$var wire 32 = B [31:0] $end
$var wire 4 > ctrl [3:0] $end
$var wire 1 $ zero $end
$var wire 32 ? A [31:0] $end
$var reg 32 @ result [31:0] $end
$upscope $end
$scope module CU $end
$var wire 7 A opcode [6:0] $end
$var reg 2 B ALUOp [1:0] $end
$var reg 1 6 ALUSrc $end
$var reg 1 5 Branch $end
$var reg 1 4 MemRead $end
$var reg 1 3 MemWrite $end
$var reg 1 2 MemtoReg $end
$var reg 1 1 RegWrite $end
$upscope $end
$scope module DMEM $end
$var wire 1 4 MemRead $end
$var wire 1 3 MemWrite $end
$var wire 32 C addr [31:0] $end
$var wire 1 ! clk $end
$var wire 32 D wdata [31:0] $end
$var reg 32 E rdata [31:0] $end
$var integer 32 F i [31:0] $end
$upscope $end
$scope module IMEM $end
$var wire 32 G addr [31:0] $end
$var wire 32 H instr [31:0] $end
$var integer 32 I i [31:0] $end
$upscope $end
$scope module IMM $end
$var wire 32 J instr [31:0] $end
$var reg 32 K imm [31:0] $end
$upscope $end
$scope module RF $end
$var wire 1 1 RegWrite $end
$var wire 32 L WriteData [31:0] $end
$var wire 1 ! clk $end
$var wire 5 M rd [4:0] $end
$var wire 1 " reset $end
$var wire 5 N rs1 [4:0] $end
$var wire 5 O rs2 [4:0] $end
$var wire 32 P ReadData2 [31:0] $end
$var wire 32 Q ReadData1 [31:0] $end
$var integer 32 R i [31:0] $end
$upscope $end
$upscope $end
$upscope $end
$enddefinitions $end
$comment Show the parameter values. $end
$dumpall
$end
#0
$dumpvars
b100000 R
b0 Q
b0 P
b101 O
b0 N
b1 M
b101 L
b101 K
b10100000000000010010011 J
b100000000 I
b10100000000000010010011 H
b0 G
b100000000 F
b0 E
b0 D
b101 C
b11 B
b10011 A
b101 @
b0 ?
b10 >
b101 =
b10 <
b11 ;
b0 :
b0 9
b0 8
b11 7
16
05
04
03
02
11
b101 0
b10 /
b101 .
b101 -
b101 ,
b10100000000000010010011 +
b0 *
b100 )
b100 (
b0 '
b0 &
b101 %
0$
0#
1"
0!
$end
#5
1!
#10
0!
#15
b1010 %
b1010 L
b1010 .
b1010 @
b1010 C
b1010 0
b1010 =
b1010 ,
b1010 K
b10 M
b1010 O
b1000 )
b101000000000000100010011 +
b101000000000000100010011 H
b101000000000000100010011 J
b1110 -
b1000 (
b100 8
b100 G
1!
0"
#20
0!
#25
b1111 %
b1111 L
b1111 .
b1111 @
b1111 C
b1010 &
b1010 D
b1010 P
b101 '
b101 ?
b101 Q
b10 7
b10 ;
b10 B
11
06
b0 ,
b0 K
b11 M
b10 O
b1 N
b110011 A
b1100 )
b1000001000000110110011 +
b1000001000000110110011 H
b1000001000000110110011 J
b1000 -
b1100 (
b1000 8
b1000 G
1!
#30
0!
#35
b0 %
b0 L
1$
b0 .
b0 @
b0 C
b0 0
b0 =
b0 &
b0 D
b0 P
b0 '
b0 ?
b0 Q
16
b11 7
b11 ;
b11 B
11
b0 M
b0 O
b0 N
b10011 A
b10000 )
b10011 +
b10011 H
b10011 J
b1100 -
b10000 (
b1100 8
b1100 G
1!
#40
0!
#45
b10100 )
b10000 -
b10100 (
b10000 8
b10000 G
1!
#50
0!
#55
b11000 )
b10100 -
b11000 (
b10100 8
b10100 G
1!
#60
0!
#65
b11100 )
b11000 -
b11100 (
b11000 8
b11000 G
1!
#70
0!
#75
b100000 )
b11100 -
b100000 (
b11100 8
b11100 G
1!
#80
0!
#85
b100100 )
b100000 -
b100100 (
b100000 8
b100000 G
1!
#90
0!
#95
b101000 )
b100100 -
b101000 (
b100100 8
b100100 G
1!
#100
0!
#105
b101100 )
b101000 -
b101100 (
b101000 8
b101000 G
1!
#110
0!
#115
b110000 )
b101100 -
b110000 (
b101100 8
b101100 G
1!
#120
0!
#125
b110100 )
b110000 -
b110100 (
b110000 8
b110000 G
1!
#130
0!
#135
b111000 )
b110100 -
b111000 (
b110100 8
b110100 G
1!
#140
0!
#145
b111100 )
b111000 -
b111100 (
b111000 8
b111000 G
1!
#150
0!
#155
b1000000 )
b111100 -
b1000000 (
b111100 8
b111100 G
1!
#160
0!
#165
b1000100 )
b1000000 -
b1000100 (
b1000000 8
b1000000 G
1!
#170
0!
#175
b1001000 )
b1000100 -
b1001000 (
b1000100 8
b1000100 G
1!
#180
0!
#185
b1001100 )
b1001000 -
b1001100 (
b1001000 8
b1001000 G
1!
#190
0!
#195
b1010000 )
b1001100 -
b1010000 (
b1001100 8
b1001100 G
1!
#200
0!
#205
b1010100 )
b1010000 -
b1010100 (
b1010000 8
b1010000 G
1!
#210
0!
#215
b1011000 )
b1010100 -
b1011000 (
b1010100 8
b1010100 G
1!
#220
0!
#225
b1011100 )
b1011000 -
b1011100 (
b1011000 8
b1011000 G
1!
#230
0!
#235
b1100000 )
b1011100 -
b1100000 (
b1011100 8
b1011100 G
1!
#240
0!
#245
b1100100 )
b1100000 -
b1100100 (
b1100000 8
b1100000 G
1!
#250
0!
#255
b1101000 )
b1100100 -
b1101000 (
b1100100 8
b1100100 G
1!
#260
0!
#265
b1101100 )
b1101000 -
b1101100 (
b1101000 8
b1101000 G
1!
#270
0!
#275
b1110000 )
b1101100 -
b1110000 (
b1101100 8
b1101100 G
1!
#280
0!
#285
b1110100 )
b1110000 -
b1110100 (
b1110000 8
b1110000 G
1!
#290
0!
#295
b1111000 )
b1110100 -
b1111000 (
b1110100 8
b1110100 G
1!
#300
0!
#305
b1111100 )
b1111000 -
b1111100 (
b1111000 8
b1111000 G
1!
#310
0!
#315
b10000000 )
b1111100 -
b10000000 (
b1111100 8
b1111100 G
1!
