mux.v
module mux(a,b,s,y);
input a;
input b;
input s;
output y;
assign y=s?b:a;
endmodule

tb_mux.v
module tb_mux;
reg a,b;
reg s;
wire y;
mux uut(.a(a),.b(b),.s(s),.y(y));
initial begin
$dumpfile("mux.vcd");
        $dumpvars(0, tb_mux);
$display("time|a|b|s|y ");
$monitor("%0t   %b|%b|%b|%b",$time, a, b, s, y);
a=1'b0;b=1'b0;s=0;#5
a=1'b0;b=1'b1;s=0;#5
a=1'b1;b=1'b0;s=0;#5
a=1'b1;b=1'b1;s=0;#5
a=1'b0;b=1'b0;s=1;#5
a=1'b0;b=1'b1;s=1;#5
a=1'b1;b=1'b0;s=1;#5
a=1'b1;b=1'b1;s=1;#5

$finish;
end
endmodule

mux.vcd
$date
	Sat Aug 22 06:14:21 2026
$end
$version
	Icarus Verilog
$end
$timescale
	1s
$end
$scope module tb_mux $end
$var wire 1 ! y $end
$var reg 1 " a $end
$var reg 1 # b $end
$var reg 1 $ s $end
$scope module uut $end
$var wire 1 " a $end
$var wire 1 # b $end
$var wire 1 $ s $end
$var wire 1 ! y $end
$upscope $end
$upscope $end
$enddefinitions $end
$comment Show the parameter values. $end
$dumpall
$end
#0
$dumpvars
0$
0#
0"
0!
$end
#5
1#
#10
1!
0#
1"
#15
1#
#20
0!
1$
0#
0"
#25
1!
1#
#30
0!
0#
1"
#35
1!
1#
